{"analyticsListId":"product","analyticsListName":"Product","url":"https://www.freshful.ro/p/100109802-taft-ceara-pentru-par-75ml","images":[{"thumbnail":{"default":"https://cdn.freshful.ro/media/cache/sylius_shop_product_thumbnail/f8/f4/8a37d9f88414884b000a4a5b8b56.jpg"},"large":{"default":"https://cdn.freshful.ro/media/cache/freshful_large/f8/f4/8a37d9f88414884b000a4a5b8b56.jpg"},"extralarge":{"default":"https://cdn.freshful.ro/media/cache/sylius_shop_product_original/f8/f4/8a37d9f88414884b000a4a5b8b56.jpg"}},{"thumbnail":{"default":"https://cdn.freshful.ro/media/cache/sylius_shop_product_thumbnail/be/c1/a4edb3fa0569268420defd876d97.jpg"},"large":{"default":"https://cdn.freshful.ro/media/cache/freshful_large/be/c1/a4edb3fa0569268420defd876d97.jpg"},"extralarge":{"default":"https://cdn.freshful.ro/media/cache/sylius_shop_product_original/be/c1/a4edb3fa0569268420defd876d97.jpg"}}],"variants":[{"code":"40152257","slug":"","name":null,"isAvailable":true,"isSelected":true}],"commercialDisclaimer":"Imaginile produselor sunt afișate cu titlu de prezentare. Facem tot posibilul să ne asigurăm că informațiile  pe care ți le oferim sunt corecte și complete, însă te rugăm să consulți întotdeauna ambalajul produsului.  Producătorul poate modifica ambalajul fără o înștiințare prealabilă, astfel că nu putem fi răspunzători  de eventuale diferențe (în termeni de culoare, formă, aspect) între imaginea afișată și cea a produsului livrat.\n","attributeGroups":[{"title":"Informatii","attributeTypes":[{"type":"text","title":null,"subtitle":null,"attributes":[{"name":"Descriere","value":"<p>Încă de la primul fixativ pe care l-a creat în urmă cu 60 de ani, Taft a devenit brand-ul de încredere care te ajută să obții coafuri perfecte, actuale.<br />\n</p><p> Oferind volum fantastic, strălucire uimitoare, culoare radiantă și faimoasă fixare puternică indiferent de vreme, fiecare produs Taft este creat special pentru nevoile individuale ale consumatorilor săi.</p>","children":[]},{"name":"Sfat depozitare (Conditii, Grade)","value":"A se păstra la loc uscat, ferit de razele directe ale soarelui și de căldură.","children":[]}]},{"type":"table","title":"Provenienta","subtitle":null,"attributes":[{"name":"Tara de origine","value":"Germania","children":[]}]}]}],"slots":[{"type":"products_carousel","title":"Produse similare","products":[{"code":"100109817","variantCode":"9000100672825","name":"Pudră de volum pentru toate tipurile de păr 10g","slug":"100109817-taft-pudra-de-volum-pentru-toate-tipurile-de-par-10g","unitPriceLabel":"2.119 Lei/l","brand":"Taft","brandCode":"1754","brandFilterCode":"taft-b1758","sku":"100109817","price":21.19,"originalPrice":null,"currencyCode":"RON","currency":"Lei","image":{"thumbnail":{"default":"https://cdn.freshful.ro/media/cache/sylius_shop_product_thumbnail/25/74/55421076342be5f124b8e0bf108e.jpg"},"large":{"default":"https://cdn.freshful.ro/media/cache/freshful_large/25/74/55421076342be5f124b8e0bf108e.jpg"},"extralarge":{"default":"https://cdn.freshful.ro/media/cache/sylius_shop_product_original/25/74/55421076342be5f124b8e0bf108e.jpg"}},"label":null,"tags":[],"isAvailable":true,"maxAvailableQuantity":12,"maxAllowedQuantity":100,"breadcrumbs":[{"code":"11","name":"Cosmetice","slug":"11-cosmetice-si-ingrijire-personala"},{"code":"1107","name":"Îngrijirea părului","slug":"1107-ingrijirea-parului"},{"code":"110702","name":"Fixativ, gel și spumă pentru păr","slug":"110702-fixativ-gel-si-spuma-par"},{"code":"100109817","name":"Pudră de volum pentru toate tipurile de păr 10g","slug":"100109817-taft-pudra-de-volum-pentru-toate-tipurile-de-par-10g"}],"activePromotion":null,"saveMe":null,"labels":[],"geniusPrice":null,"geniusUnitPricePerLabel":null,"banner":null,"discountLabel":null,"geniusDiscountLabel":null,"badge":null},{"code":"100110029","variantCode":"9000101208504","name":"Pastă modelatoare Invisible 100ml","slug":"100110029-syoss-pasta-modelatoare-invisible-100ml","unitPriceLabel":"282,18 Lei/l","brand":"Syoss","brandCode":"1761","brandFilterCode":"syoss-b1765","sku":"100110029","price":28.5,"originalPrice":null,"currencyCode":"RON","currency":"Lei","image":{"thumbnail":{"default":"https://cdn.freshful.ro/media/cache/sylius_shop_product_thumbnail/b5/a6/afccb033a7bec93ae446a98448c6.jpg"},"large":{"default":"https://cdn.freshful.ro/media/cache/freshful_large/b5/a6/afccb033a7bec93ae446a98448c6.jpg"},"extralarge":{"default":"https://cdn.freshful.ro/media/cache/sylius_shop_product_original/b5/a6/afccb033a7bec93ae446a98448c6.jpg"}},"label":null,"tags":[],"isAvailable":true,"maxAvailableQuantity":12,"maxAllowedQuantity":100,"breadcrumbs":[{"code":"11","name":"Cosmetice","slug":"11-cosmetice-si-ingrijire-personala"},{"code":"1107","name":"Îngrijirea părului","slug":"1107-ingrijirea-parului"},{"code":"110702","name":"Fixativ, gel și spumă pentru păr","slug":"110702-fixativ-gel-si-spuma-par"},{"code":"100110029","name":"Pastă modelatoare Invisible 100ml","slug":"100110029-syoss-pasta-modelatoare-invisible-100ml"}],"activePromotion":null,"saveMe":null,"labels":[],"geniusPrice":null,"geniusUnitPricePerLabel":null,"banner":null,"discountLabel":null,"geniusDiscountLabel":null,"badge":null},{"code":"100109793","variantCode":"3838824258553","name":"Gel de păr Looks V12, 150ml","slug":"100109793-taft-gel-de-par-looks-v12-150ml","unitPriceLabel":"125,93 Lei/l","brand":"Taft","brandCode":"1754","brandFilterCode":"taft-b1758","sku":"100109793","price":18.89,"originalPrice":null,"currencyCode":"RON","currency":"Lei","image":{"thumbnail":{"default":"https://cdn.freshful.ro/media/cache/sylius_shop_product_thumbnail/1e/14/0d1f7f9fd4f5e9cfa4e095d3ba25.jpg"},"large":{"default":"https://cdn.freshful.ro/media/cache/freshful_large/1e/14/0d1f7f9fd4f5e9cfa4e095d3ba25.jpg"},"extralarge":{"default":"https://cdn.freshful.ro/media/cache/sylius_shop_product_original/1e/14/0d1f7f9fd4f5e9cfa4e095d3ba25.jpg"}},"label":null,"tags":[],"isAvailable":true,"maxAvailableQuantity":11,"maxAllowedQuantity":100,"breadcrumbs":[{"code":"11","name":"Cosmetice","slug":"11-cosmetice-si-ingrijire-personala"},{"code":"1107","name":"Îngrijirea părului","slug":"1107-ingrijirea-parului"},{"code":"110702","name":"Fixativ, gel și spumă pentru păr","slug":"110702-fixativ-gel-si-spuma-par"},{"code":"100109793","name":"Gel de păr Looks V12, 150ml","slug":"100109793-taft-gel-de-par-looks-v12-150ml"}],"activePromotion":null,"saveMe":null,"labels":[],"geniusPrice":null,"geniusUnitPricePerLabel":null,"banner":null,"discountLabel":null,"geniusDiscountLabel":null,"badge":null},{"code":"100110020","variantCode":"9000100591058","name":"Gel de păr Max Hold 250ml","slug":"100110020-syoss-gel-de-par-max-hold-250ml","unitPriceLabel":"91,6 Lei/l","brand":"Syoss","brandCode":"1761","brandFilterCode":"syoss-b1765","sku":"100110020","price":22.9,"originalPrice":null,"currencyCode":"RON","currency":"Lei","image":{"thumbnail":{"default":"https://cdn.freshful.ro/media/cache/sylius_shop_product_thumbnail/25/46/84752574d538f9dc16fd92b4837b.jpg"},"large":{"default":"https://cdn.freshful.ro/media/cache/freshful_large/25/46/84752574d538f9dc16fd92b4837b.jpg"},"extralarge":{"default":"https://cdn.freshful.ro/media/cache/sylius_shop_product_original/25/46/84752574d538f9dc16fd92b4837b.jpg"}},"label":null,"tags":[],"isAvailable":true,"maxAvailableQuantity":9,"maxAllowedQuantity":100,"breadcrumbs":[{"code":"11","name":"Cosmetice","slug":"11-cosmetice-si-ingrijire-personala"},{"code":"1107","name":"Îngrijirea părului","slug":"1107-ingrijirea-parului"},{"code":"110702","name":"Fixativ, gel și spumă pentru păr","slug":"110702-fixativ-gel-si-spuma-par"},{"code":"100110020","name":"Gel de păr Max Hold 250ml","slug":"100110020-syoss-gel-de-par-max-hold-250ml"}],"activePromotion":null,"saveMe":null,"labels":[],"geniusPrice":null,"geniusUnitPricePerLabel":null,"banner":null,"discountLabel":null,"geniusDiscountLabel":null,"badge":null},{"code":"100110031","variantCode":"9000101208542","name":"Pastă modelatoare pentru păr cu efect mat 100ml","slug":"100110031-syoss-pasta-modelatoare-pentru-par-cu-efect-mat-100ml","unitPriceLabel":"282,18 Lei/l","brand":"Syoss","brandCode":"1761","brandFilterCode":"syoss-b1765","sku":"100110031","price":28.5,"originalPrice":null,"currencyCode":"RON","currency":"Lei","image":{"thumbnail":{"default":"https://cdn.freshful.ro/media/cache/sylius_shop_product_thumbnail/e6/e8/a14ef9681a219d34b4242dca4177.jpg"},"large":{"default":"https://cdn.freshful.ro/media/cache/freshful_large/e6/e8/a14ef9681a219d34b4242dca4177.jpg"},"extralarge":{"default":"https://cdn.freshful.ro/media/cache/sylius_shop_product_original/e6/e8/a14ef9681a219d34b4242dca4177.jpg"}},"label":null,"tags":[],"isAvailable":true,"maxAvailableQuantity":10,"maxAllowedQuantity":100,"breadcrumbs":[{"code":"11","name":"Cosmetice","slug":"11-cosmetice-si-ingrijire-personala"},{"code":"1107","name":"Îngrijirea părului","slug":"1107-ingrijirea-parului"},{"code":"110702","name":"Fixativ, gel și spumă pentru păr","slug":"110702-fixativ-gel-si-spuma-par"},{"code":"100110031","name":"Pastă modelatoare pentru păr cu efect mat 100ml","slug":"100110031-syoss-pasta-modelatoare-pentru-par-cu-efect-mat-100ml"}],"activePromotion":null,"saveMe":null,"labels":[],"geniusPrice":null,"geniusUnitPricePerLabel":null,"banner":null,"discountLabel":null,"geniusDiscountLabel":null,"badge":null},{"code":"100033718","variantCode":"42277309","name":"Gel-cremă păr pentru bărbați 150ml","slug":"100033718-nivea-gel-crema-par-pentru-barbati-150ml","unitPriceLabel":"179,33 Lei/l","brand":"Nivea","brandCode":"316","brandFilterCode":"nivea-b317","sku":"100033718","price":26.9,"originalPrice":null,"currencyCode":"RON","currency":"Lei","image":{"thumbnail":{"default":"https://cdn.freshful.ro/media/cache/sylius_shop_product_thumbnail/61/3b/cc71bb43d4548fdeffce364c46f1.jpg"},"large":{"default":"https://cdn.freshful.ro/media/cache/freshful_large/61/3b/cc71bb43d4548fdeffce364c46f1.jpg"},"extralarge":{"default":"https://cdn.freshful.ro/media/cache/sylius_shop_product_original/61/3b/cc71bb43d4548fdeffce364c46f1.jpg"}},"label":null,"tags":[],"isAvailable":true,"maxAvailableQuantity":10,"maxAllowedQuantity":100,"breadcrumbs":[{"code":"11","name":"Cosmetice","slug":"11-cosmetice-si-ingrijire-personala"},{"code":"1107","name":"Îngrijirea părului","slug":"1107-ingrijirea-parului"},{"code":"110702","name":"Fixativ, gel și spumă pentru păr","slug":"110702-fixativ-gel-si-spuma-par"},{"code":"100033718","name":"Gel-cremă păr pentru bărbați 150ml","slug":"100033718-nivea-gel-crema-par-pentru-barbati-150ml"}],"activePromotion":null,"saveMe":null,"labels":[],"geniusPrice":null,"geniusUnitPricePerLabel":null,"banner":null,"discountLabel":null,"geniusDiscountLabel":null,"badge":null},{"code":"100109928","variantCode":"100109928","name":"Gel pentru păr rezistent la apă 150ml ","slug":"100109928-got2b-gel-pentru-par-rezistent-la-apa-150ml","unitPriceLabel":"156,67 Lei/l","brand":"got2b","brandCode":"1757","brandFilterCode":"got2b-b1761","sku":"100109928","price":23.5,"originalPrice":null,"currencyCode":"RON","currency":"Lei","image":{"thumbnail":{"default":"https://cdn.freshful.ro/media/cache/sylius_shop_product_thumbnail/83/c3/f79bbe57d0191dd7f7b0d18ee2ee.jpg"},"large":{"default":"https://cdn.freshful.ro/media/cache/freshful_large/83/c3/f79bbe57d0191dd7f7b0d18ee2ee.jpg"},"extralarge":{"default":"https://cdn.freshful.ro/media/cache/sylius_shop_product_original/83/c3/f79bbe57d0191dd7f7b0d18ee2ee.jpg"}},"label":null,"tags":[],"isAvailable":true,"maxAvailableQuantity":9,"maxAllowedQuantity":100,"breadcrumbs":[{"code":"11","name":"Cosmetice","slug":"11-cosmetice-si-ingrijire-personala"},{"code":"1107","name":"Îngrijirea părului","slug":"1107-ingrijirea-parului"},{"code":"110702","name":"Fixativ, gel și spumă pentru păr","slug":"110702-fixativ-gel-si-spuma-par"},{"code":"100109928","name":"Gel pentru păr rezistent la apă 150ml ","slug":"100109928-got2b-gel-pentru-par-rezistent-la-apa-150ml"}],"activePromotion":null,"saveMe":null,"labels":[],"geniusPrice":null,"geniusUnitPricePerLabel":null,"banner":null,"discountLabel":null,"geniusDiscountLabel":null,"badge":null},{"code":"100109801","variantCode":"9000100876452","name":"Gel de păr Power Invisible (5) 150ml","slug":"100109801-taft-gel-de-par-power-invisible-5-150ml","unitPriceLabel":"99,93 Lei/l","brand":"Taft","brandCode":"1754","brandFilterCode":"taft-b1758","sku":"100109801","price":14.99,"originalPrice":null,"currencyCode":"RON","currency":"Lei","image":{"thumbnail":{"default":"https://cdn.freshful.ro/media/cache/sylius_shop_product_thumbnail/1e/8a/8d19afb1c38fe499a6b4538dbbfa.jpg"},"large":{"default":"https://cdn.freshful.ro/media/cache/freshful_large/1e/8a/8d19afb1c38fe499a6b4538dbbfa.jpg"},"extralarge":{"default":"https://cdn.freshful.ro/media/cache/sylius_shop_product_original/1e/8a/8d19afb1c38fe499a6b4538dbbfa.jpg"}},"label":{"text":"Profită acum","backgroundColor":"#FF9903","textColor":"#FFFFFF"},"tags":[{"type":"vegan","text":"Vegan","icon":"https://cdn.freshful.ro/assets/product_tags/vegan.svg","iconPng":"https://cdn.freshful.ro/assets/product_tags/vegan.png","backgroundColor":"#ECF9F8","textColor":"#33A39C"}],"isAvailable":true,"maxAvailableQuantity":10,"maxAllowedQuantity":100,"breadcrumbs":[{"code":"11","name":"Cosmetice","slug":"11-cosmetice-si-ingrijire-personala"},{"code":"1107","name":"Îngrijirea părului","slug":"1107-ingrijirea-parului"},{"code":"110702","name":"Fixativ, gel și spumă pentru păr","slug":"110702-fixativ-gel-si-spuma-par"},{"code":"100109801","name":"Gel de păr Power Invisible (5) 150ml","slug":"100109801-taft-gel-de-par-power-invisible-5-150ml"}],"activePromotion":{"code":"special-colorare-styling-feb23","name":"Preț avantajos","targetQuantity":null},"saveMe":null,"labels":[{"type":"v1","items":[{"text":"Profită acum","backgroundColor":"#FF9903","textColor":"#FFFFFF"}]}],"geniusPrice":null,"geniusUnitPricePerLabel":null,"banner":{"text":"Preț avantajos","textColor":"#F95510","bgColor":"#FEF1CD","icon":null,"link":"https://www.freshful.ro/oferte/special-colorare-styling-feb23","type":"promo","analyticsEventType":"select_promotion","analyticsEventPayload":{"promotion_id":"special-colorare-styling-feb23","promotion_name":"Colorare și styling"}},"discountLabel":null,"geniusDiscountLabel":null,"badge":null},{"code":"100033719","variantCode":"42246534","name":"Gel-Cremă pentru păr Care&Hold 150ml","slug":"100033719-nivea-gel-crema-pentru-par-care-hold-150ml","unitPriceLabel":"173,27 Lei/l","brand":"Nivea","brandCode":"316","brandFilterCode":"nivea-b317","sku":"100033719","price":25.99,"originalPrice":null,"currencyCode":"RON","currency":"Lei","image":{"thumbnail":{"default":"https://cdn.freshful.ro/media/cache/sylius_shop_product_thumbnail/4c/ed/f8f3bb52559d8a9f94187635fae4.jpg"},"large":{"default":"https://cdn.freshful.ro/media/cache/freshful_large/4c/ed/f8f3bb52559d8a9f94187635fae4.jpg"},"extralarge":{"default":"https://cdn.freshful.ro/media/cache/sylius_shop_product_original/4c/ed/f8f3bb52559d8a9f94187635fae4.jpg"}},"label":null,"tags":[],"isAvailable":true,"maxAvailableQuantity":10,"maxAllowedQuantity":100,"breadcrumbs":[{"code":"11","name":"Cosmetice","slug":"11-cosmetice-si-ingrijire-personala"},{"code":"1107","name":"Îngrijirea părului","slug":"1107-ingrijirea-parului"},{"code":"110702","name":"Fixativ, gel și spumă pentru păr","slug":"110702-fixativ-gel-si-spuma-par"},{"code":"100033719","name":"Gel-Cremă pentru păr Care&Hold 150ml","slug":"100033719-nivea-gel-crema-pentru-par-care-hold-150ml"}],"activePromotion":null,"saveMe":null,"labels":[],"geniusPrice":null,"geniusUnitPricePerLabel":null,"banner":null,"discountLabel":null,"geniusDiscountLabel":null,"badge":null},{"code":"100109797","variantCode":"9000101034523","name":"Gel de păr Irresistible Power 150ml","slug":"100109797-taft-gel-de-par-irresistible-power-150ml","unitPriceLabel":"107,27 Lei/l","brand":"Taft","brandCode":"1754","brandFilterCode":"taft-b1758","sku":"100109797","price":16.09,"originalPrice":null,"currencyCode":"RON","currency":"Lei","image":{"thumbnail":{"default":"https://cdn.freshful.ro/media/cache/sylius_shop_product_thumbnail/c3/52/83ca3ce061deb1048fb745984a5a.jpg"},"large":{"default":"https://cdn.freshful.ro/media/cache/freshful_large/c3/52/83ca3ce061deb1048fb745984a5a.jpg"},"extralarge":{"default":"https://cdn.freshful.ro/media/cache/sylius_shop_product_original/c3/52/83ca3ce061deb1048fb745984a5a.jpg"}},"label":null,"tags":[],"isAvailable":true,"maxAvailableQuantity":3,"maxAllowedQuantity":100,"breadcrumbs":[{"code":"11","name":"Cosmetice","slug":"11-cosmetice-si-ingrijire-personala"},{"code":"1107","name":"Îngrijirea părului","slug":"1107-ingrijirea-parului"},{"code":"110702","name":"Fixativ, gel și spumă pentru păr","slug":"110702-fixativ-gel-si-spuma-par"},{"code":"100109797","name":"Gel de păr Irresistible Power 150ml","slug":"100109797-taft-gel-de-par-irresistible-power-150ml"}],"activePromotion":null,"saveMe":null,"labels":[],"geniusPrice":null,"geniusUnitPricePerLabel":null,"banner":null,"discountLabel":null,"geniusDiscountLabel":null,"badge":null}],"analyticsListId":"product-slot_produse-similare","analyticsListName":"Product Slot - Produse similare"}],"metaTitle":"Ceară pentru păr 75ml - Prospețime și varietate","metaKeywords":null,"metaDescription":"Comandă Ceară pentru păr 75ml. Livrăm când dorești, cu mașini frigorifice. Gamă variată de bunătăți proaspete, de la producători locali. Hai pe Freshful.ro","code":"100109802","variantCode":"40152257","name":"Ceară pentru păr 75ml","slug":"100109802-taft-ceara-pentru-par-75ml","unitPriceLabel":"194,68 Lei/l","brand":"Taft","brandCode":"1754","brandFilterCode":"taft-b1758","sku":"100109802","price":14.99,"originalPrice":null,"currencyCode":"RON","currency":"Lei","image":{"thumbnail":{"default":"https://cdn.freshful.ro/media/cache/sylius_shop_product_thumbnail/f8/f4/8a37d9f88414884b000a4a5b8b56.jpg"},"large":{"default":"https://cdn.freshful.ro/media/cache/freshful_large/f8/f4/8a37d9f88414884b000a4a5b8b56.jpg"},"extralarge":{"default":"https://cdn.freshful.ro/media/cache/sylius_shop_product_original/f8/f4/8a37d9f88414884b000a4a5b8b56.jpg"}},"label":{"text":"Profită acum","backgroundColor":"#FF9903","textColor":"#FFFFFF"},"tags":[],"isAvailable":true,"maxAvailableQuantity":21,"maxAllowedQuantity":100,"breadcrumbs":[{"code":"11","name":"Cosmetice","slug":"11-cosmetice-si-ingrijire-personala"},{"code":"1107","name":"Îngrijirea părului","slug":"1107-ingrijirea-parului"},{"code":"110702","name":"Fixativ, gel și spumă pentru păr","slug":"110702-fixativ-gel-si-spuma-par"},{"code":"100109802","name":"Ceară pentru păr 75ml","slug":"100109802-taft-ceara-pentru-par-75ml"}],"activePromotion":{"code":"special-colorare-styling-feb23","name":"Preț avantajos","targetQuantity":null},"saveMe":null,"labels":[{"type":"v1","items":[{"text":"Profită acum","backgroundColor":"#FF9903","textColor":"#FFFFFF"}]}],"geniusPrice":null,"geniusUnitPricePerLabel":null,"banner":{"text":"Preț avantajos","textColor":"#F95510","bgColor":"#FEF1CD","icon":null,"link":"https://www.freshful.ro/oferte/special-colorare-styling-feb23","type":"promo","analyticsEventType":"select_promotion","analyticsEventPayload":{"promotion_id":"special-colorare-styling-feb23","promotion_name":"Colorare și styling"}},"discountLabel":null,"geniusDiscountLabel":null,"badge":null}