{"analyticsListId":"product","analyticsListName":"Product","url":"https://www.freshful.ro/p/100137982-biodeck-farfurii-biodegradabile-din-trestie-de-zahar-12-buc","images":[{"thumbnail":{"default":"https://cdn.freshful.ro/media/cache/sylius_shop_product_thumbnail/46/ca/e65d876670208f252e3980e8465f.jpg"},"large":{"default":"https://cdn.freshful.ro/media/cache/freshful_large/46/ca/e65d876670208f252e3980e8465f.jpg"},"extralarge":{"default":"https://cdn.freshful.ro/media/cache/sylius_shop_product_original/46/ca/e65d876670208f252e3980e8465f.jpg"}},{"thumbnail":{"default":"https://cdn.freshful.ro/media/cache/sylius_shop_product_thumbnail/2b/1d/f4d26fc9b6028585bf9ef0958772.jpg"},"large":{"default":"https://cdn.freshful.ro/media/cache/freshful_large/2b/1d/f4d26fc9b6028585bf9ef0958772.jpg"},"extralarge":{"default":"https://cdn.freshful.ro/media/cache/sylius_shop_product_original/2b/1d/f4d26fc9b6028585bf9ef0958772.jpg"}}],"variants":[{"code":"100137982","slug":"","name":null,"isAvailable":true,"isSelected":true}],"commercialDisclaimer":"Imaginile produselor sunt afișate cu titlu de prezentare. Facem tot posibilul să ne asigurăm că informațiile  pe care ți le oferim sunt corecte și complete, însă te rugăm să consulți întotdeauna ambalajul produsului.  Producătorul poate modifica ambalajul fără o înștiințare prealabilă, astfel că nu putem fi răspunzători  de eventuale diferențe (în termeni de culoare, formă, aspect) între imaginea afișată și cea a produsului livrat.\n","attributeGroups":[{"title":"Informatii","attributeTypes":[{"type":"text","title":null,"subtitle":null,"attributes":[{"name":"Descriere","value":"Farfuriile rotunde din trestie de zahar Biodeck au un diametru de 17 cm. <br />\n<br />\nProdusele sunt realizate din trestie de zahăr, 100% biodegrabile și compostabile.<br />\n<br />\nFarfuriile sunt făcute din plante și au la bază pulpă din trestia de zahăr. <br />\n<br />\nÎn mod normal, după extragerea sucului, aceasta resursă ar urma să fie arsă, un proces poluant pentru mediu.","children":[]},{"name":"Sfat depozitare (Conditii, Grade)","value":"A se păstra la loc uscat și răcoros, ferit de îngheț și de razele soarelui.","children":[]}]},{"type":"table","title":"Provenienta","subtitle":null,"attributes":[{"name":"Tara de origine","value":"China","children":[]},{"name":"Nume producator","value":"S.C BIODECK S.A","children":[]},{"name":"Website producator","value":"https://www.biodeck.ro","children":[]}]}]}],"slots":[{"type":"products_carousel","title":"Produse similare","products":[{"code":"100137980","variantCode":"100137980","name":"Pahare carton zero plastic bio Artwork 240ml, 25 buc","slug":"100137980-biodeck-pahare-carton-zero-plastic-bio-artwork-240ml-25-buc","unitPriceLabel":"","brand":"Biodeck","brandCode":"299","brandFilterCode":"biodeck-b300","sku":"100137980","price":16.99,"originalPrice":null,"currencyCode":"RON","currency":"Lei","image":{"thumbnail":{"default":"https://cdn.freshful.ro/media/cache/sylius_shop_product_thumbnail/de/0f/f36306b6bec24eb6717be694ab0a.jpg"},"large":{"default":"https://cdn.freshful.ro/media/cache/freshful_large/de/0f/f36306b6bec24eb6717be694ab0a.jpg"},"extralarge":{"default":"https://cdn.freshful.ro/media/cache/sylius_shop_product_original/de/0f/f36306b6bec24eb6717be694ab0a.jpg"}},"label":null,"tags":[{"type":"bio","text":"Bio","icon":"https://cdn.freshful.ro/assets/product_tags/bio.svg","iconPng":"https://cdn.freshful.ro/assets/product_tags/bio.png","backgroundColor":"#ECF6E9","textColor":"#399225"}],"isAvailable":true,"maxAvailableQuantity":82,"maxAllowedQuantity":100,"breadcrumbs":[{"code":"14","name":"Casă și agrement","slug":"14-casa-si-agrement"},{"code":"1403","name":"Articole de menaj","slug":"1403-articole-de-menaj"},{"code":"140303","name":"Veselă de unică folosință","slug":"140303-vesela-de-unica-folosinta"},{"code":"100137980","name":"Pahare carton zero plastic bio Artwork 240ml, 25 buc","slug":"100137980-biodeck-pahare-carton-zero-plastic-bio-artwork-240ml-25-buc"}],"activePromotion":null,"saveMe":null,"labels":[],"geniusPrice":null,"geniusUnitPricePerLabel":null,"banner":null,"discountLabel":null,"geniusDiscountLabel":null,"badge":null},{"code":"100137984","variantCode":"100137984","name":"Paie biodegradabile și compostabile 5mm, 250 buc","slug":"100137984-biodeck-paie-biodegradabile-si-compostabile-5mm-250-buc","unitPriceLabel":"","brand":"Biodeck","brandCode":"299","brandFilterCode":"biodeck-b300","sku":"100137984","price":19.99,"originalPrice":null,"currencyCode":"RON","currency":"Lei","image":{"thumbnail":{"default":"https://cdn.freshful.ro/media/cache/sylius_shop_product_thumbnail/ee/11/ed97895f41f98266b74b52fc0b72.jpg"},"large":{"default":"https://cdn.freshful.ro/media/cache/freshful_large/ee/11/ed97895f41f98266b74b52fc0b72.jpg"},"extralarge":{"default":"https://cdn.freshful.ro/media/cache/sylius_shop_product_original/ee/11/ed97895f41f98266b74b52fc0b72.jpg"}},"label":null,"tags":[{"type":"bio","text":"Bio","icon":"https://cdn.freshful.ro/assets/product_tags/bio.svg","iconPng":"https://cdn.freshful.ro/assets/product_tags/bio.png","backgroundColor":"#ECF6E9","textColor":"#399225"}],"isAvailable":true,"maxAvailableQuantity":48,"maxAllowedQuantity":100,"breadcrumbs":[{"code":"14","name":"Casă și agrement","slug":"14-casa-si-agrement"},{"code":"1403","name":"Articole de menaj","slug":"1403-articole-de-menaj"},{"code":"140303","name":"Veselă de unică folosință","slug":"140303-vesela-de-unica-folosinta"},{"code":"100137984","name":"Paie biodegradabile și compostabile 5mm, 250 buc","slug":"100137984-biodeck-paie-biodegradabile-si-compostabile-5mm-250-buc"}],"activePromotion":null,"saveMe":null,"labels":[],"geniusPrice":null,"geniusUnitPricePerLabel":null,"banner":null,"discountLabel":null,"geniusDiscountLabel":null,"badge":null},{"code":"100132452","variantCode":"100132452","name":"Farfurii trestie biodegradabile 22cm 12 bucăți","slug":"100132452-biodeck-farfurii-trestie-biodegradabile-22cm-12-bucati","unitPriceLabel":"","brand":"Biodeck","brandCode":"299","brandFilterCode":"biodeck-b300","sku":"100132452","price":11.19,"originalPrice":null,"currencyCode":"RON","currency":"Lei","image":{"thumbnail":{"default":"https://cdn.freshful.ro/media/cache/sylius_shop_product_thumbnail/35/c4/28ede1c194f7ee818c12d782b9f5.jpg"},"large":{"default":"https://cdn.freshful.ro/media/cache/freshful_large/35/c4/28ede1c194f7ee818c12d782b9f5.jpg"},"extralarge":{"default":"https://cdn.freshful.ro/media/cache/sylius_shop_product_original/35/c4/28ede1c194f7ee818c12d782b9f5.jpg"}},"label":null,"tags":[{"type":"bio","text":"Bio","icon":"https://cdn.freshful.ro/assets/product_tags/bio.svg","iconPng":"https://cdn.freshful.ro/assets/product_tags/bio.png","backgroundColor":"#ECF6E9","textColor":"#399225"}],"isAvailable":true,"maxAvailableQuantity":43,"maxAllowedQuantity":100,"breadcrumbs":[{"code":"14","name":"Casă și agrement","slug":"14-casa-si-agrement"},{"code":"1403","name":"Articole de menaj","slug":"1403-articole-de-menaj"},{"code":"140303","name":"Veselă de unică folosință","slug":"140303-vesela-de-unica-folosinta"},{"code":"100132452","name":"Farfurii trestie biodegradabile 22cm 12 bucăți","slug":"100132452-biodeck-farfurii-trestie-biodegradabile-22cm-12-bucati"}],"activePromotion":null,"saveMe":null,"labels":[],"geniusPrice":null,"geniusUnitPricePerLabel":null,"banner":null,"discountLabel":null,"geniusDiscountLabel":null,"badge":null},{"code":"100137979","variantCode":"100137979","name":"Pahare carton zero plastic bio Artwork 120ml, 25 buc","slug":"100137979-biodeck-pahare-carton-zero-plastic-bio-artwork-120ml-25-buc","unitPriceLabel":"","brand":"Biodeck","brandCode":"299","brandFilterCode":"biodeck-b300","sku":"100137979","price":11.99,"originalPrice":null,"currencyCode":"RON","currency":"Lei","image":{"thumbnail":{"default":"https://cdn.freshful.ro/media/cache/sylius_shop_product_thumbnail/4d/40/26df779211a49c6699547c27c98a.jpg"},"large":{"default":"https://cdn.freshful.ro/media/cache/freshful_large/4d/40/26df779211a49c6699547c27c98a.jpg"},"extralarge":{"default":"https://cdn.freshful.ro/media/cache/sylius_shop_product_original/4d/40/26df779211a49c6699547c27c98a.jpg"}},"label":null,"tags":[{"type":"bio","text":"Bio","icon":"https://cdn.freshful.ro/assets/product_tags/bio.svg","iconPng":"https://cdn.freshful.ro/assets/product_tags/bio.png","backgroundColor":"#ECF6E9","textColor":"#399225"}],"isAvailable":true,"maxAvailableQuantity":65,"maxAllowedQuantity":100,"breadcrumbs":[{"code":"14","name":"Casă și agrement","slug":"14-casa-si-agrement"},{"code":"1403","name":"Articole de menaj","slug":"1403-articole-de-menaj"},{"code":"140303","name":"Veselă de unică folosință","slug":"140303-vesela-de-unica-folosinta"},{"code":"100137979","name":"Pahare carton zero plastic bio Artwork 120ml, 25 buc","slug":"100137979-biodeck-pahare-carton-zero-plastic-bio-artwork-120ml-25-buc"}],"activePromotion":null,"saveMe":null,"labels":[],"geniusPrice":null,"geniusUnitPricePerLabel":null,"banner":null,"discountLabel":null,"geniusDiscountLabel":null,"badge":null},{"code":"100002978","variantCode":"100002978","name":"Palete cafea din lemn, ambalaj individual 14cm 100 buc","slug":"100002978-biodeck-palete-cafea-din-lemn-ambalaj-individual-14cm-100-buc","unitPriceLabel":"","brand":"Biodeck","brandCode":"299","brandFilterCode":"biodeck-b300","sku":"100002978","price":19.9,"originalPrice":null,"currencyCode":"RON","currency":"Lei","image":{"thumbnail":{"default":"https://cdn.freshful.ro/media/cache/sylius_shop_product_thumbnail/6d/6b/3de591a683e5ae9042c1a988675b.jpg"},"large":{"default":"https://cdn.freshful.ro/media/cache/freshful_large/6d/6b/3de591a683e5ae9042c1a988675b.jpg"},"extralarge":{"default":"https://cdn.freshful.ro/media/cache/sylius_shop_product_original/6d/6b/3de591a683e5ae9042c1a988675b.jpg"}},"label":null,"tags":[{"type":"bio","text":"Bio","icon":"https://cdn.freshful.ro/assets/product_tags/bio.svg","iconPng":"https://cdn.freshful.ro/assets/product_tags/bio.png","backgroundColor":"#ECF6E9","textColor":"#399225"}],"isAvailable":true,"maxAvailableQuantity":34,"maxAllowedQuantity":100,"breadcrumbs":[{"code":"14","name":"Casă și agrement","slug":"14-casa-si-agrement"},{"code":"1403","name":"Articole de menaj","slug":"1403-articole-de-menaj"},{"code":"140303","name":"Veselă de unică folosință","slug":"140303-vesela-de-unica-folosinta"},{"code":"100002978","name":"Palete cafea din lemn, ambalaj individual 14cm 100 buc","slug":"100002978-biodeck-palete-cafea-din-lemn-ambalaj-individual-14cm-100-buc"}],"activePromotion":null,"saveMe":null,"labels":[],"geniusPrice":null,"geniusUnitPricePerLabel":null,"banner":null,"discountLabel":null,"geniusDiscountLabel":null,"badge":null},{"code":"100002972","variantCode":"100002972","name":"Furculițe lemn 16.5cm 12 buc","slug":"100002972-biodeck-furculite-lemn-16-5cm-12-buc","unitPriceLabel":"","brand":"Biodeck","brandCode":"299","brandFilterCode":"biodeck-b300","sku":"100002972","price":8.99,"originalPrice":null,"currencyCode":"RON","currency":"Lei","image":{"thumbnail":{"default":"https://cdn.freshful.ro/media/cache/sylius_shop_product_thumbnail/0d/cf/23b38bf32d71f69e3ac1eebe68f4.jpg"},"large":{"default":"https://cdn.freshful.ro/media/cache/freshful_large/0d/cf/23b38bf32d71f69e3ac1eebe68f4.jpg"},"extralarge":{"default":"https://cdn.freshful.ro/media/cache/sylius_shop_product_original/0d/cf/23b38bf32d71f69e3ac1eebe68f4.jpg"}},"label":null,"tags":[{"type":"bio","text":"Bio","icon":"https://cdn.freshful.ro/assets/product_tags/bio.svg","iconPng":"https://cdn.freshful.ro/assets/product_tags/bio.png","backgroundColor":"#ECF6E9","textColor":"#399225"}],"isAvailable":true,"maxAvailableQuantity":67,"maxAllowedQuantity":100,"breadcrumbs":[{"code":"14","name":"Casă și agrement","slug":"14-casa-si-agrement"},{"code":"1403","name":"Articole de menaj","slug":"1403-articole-de-menaj"},{"code":"140303","name":"Veselă de unică folosință","slug":"140303-vesela-de-unica-folosinta"},{"code":"100002972","name":"Furculițe lemn 16.5cm 12 buc","slug":"100002972-biodeck-furculite-lemn-16-5cm-12-buc"}],"activePromotion":null,"saveMe":null,"labels":[],"geniusPrice":null,"geniusUnitPricePerLabel":null,"banner":null,"discountLabel":null,"geniusDiscountLabel":null,"badge":null},{"code":"100143053","variantCode":"100143053","name":"Farfurii carton rotunde Oceania 18cm 12 bucăți","slug":"100143053-biodeck-farfurii-carton-rotunde-oceania-18cm-12-bucati","unitPriceLabel":"","brand":"Biodeck","brandCode":"299","brandFilterCode":"biodeck-b300","sku":"100143053","price":6.49,"originalPrice":null,"currencyCode":"RON","currency":"Lei","image":{"thumbnail":{"default":"https://cdn.freshful.ro/media/cache/sylius_shop_product_thumbnail/c0/35/2aac9826dbfaf0ebdde049cdbd67.jpg"},"large":{"default":"https://cdn.freshful.ro/media/cache/freshful_large/c0/35/2aac9826dbfaf0ebdde049cdbd67.jpg"},"extralarge":{"default":"https://cdn.freshful.ro/media/cache/sylius_shop_product_original/c0/35/2aac9826dbfaf0ebdde049cdbd67.jpg"}},"label":null,"tags":[{"type":"bio","text":"Bio","icon":"https://cdn.freshful.ro/assets/product_tags/bio.svg","iconPng":"https://cdn.freshful.ro/assets/product_tags/bio.png","backgroundColor":"#ECF6E9","textColor":"#399225"}],"isAvailable":true,"maxAvailableQuantity":73,"maxAllowedQuantity":100,"breadcrumbs":[{"code":"14","name":"Casă și agrement","slug":"14-casa-si-agrement"},{"code":"1403","name":"Articole de menaj","slug":"1403-articole-de-menaj"},{"code":"140303","name":"Veselă de unică folosință","slug":"140303-vesela-de-unica-folosinta"},{"code":"100143053","name":"Farfurii carton rotunde Oceania 18cm 12 bucăți","slug":"100143053-biodeck-farfurii-carton-rotunde-oceania-18cm-12-bucati"}],"activePromotion":null,"saveMe":null,"labels":[],"geniusPrice":null,"geniusUnitPricePerLabel":null,"banner":null,"discountLabel":null,"geniusDiscountLabel":null,"badge":null},{"code":"100002973","variantCode":"100002973","name":"Linguri lemn 16.5cm 12 buc","slug":"100002973-biodeck-linguri-lemn-16-5cm-12-buc","unitPriceLabel":"","brand":"Biodeck","brandCode":"299","brandFilterCode":"biodeck-b300","sku":"100002973","price":8.99,"originalPrice":null,"currencyCode":"RON","currency":"Lei","image":{"thumbnail":{"default":"https://cdn.freshful.ro/media/cache/sylius_shop_product_thumbnail/80/2b/f42e64a135837d0b64f498837886.jpg"},"large":{"default":"https://cdn.freshful.ro/media/cache/freshful_large/80/2b/f42e64a135837d0b64f498837886.jpg"},"extralarge":{"default":"https://cdn.freshful.ro/media/cache/sylius_shop_product_original/80/2b/f42e64a135837d0b64f498837886.jpg"}},"label":null,"tags":[{"type":"bio","text":"Bio","icon":"https://cdn.freshful.ro/assets/product_tags/bio.svg","iconPng":"https://cdn.freshful.ro/assets/product_tags/bio.png","backgroundColor":"#ECF6E9","textColor":"#399225"}],"isAvailable":true,"maxAvailableQuantity":81,"maxAllowedQuantity":100,"breadcrumbs":[{"code":"14","name":"Casă și agrement","slug":"14-casa-si-agrement"},{"code":"1403","name":"Articole de menaj","slug":"1403-articole-de-menaj"},{"code":"140303","name":"Veselă de unică folosință","slug":"140303-vesela-de-unica-folosinta"},{"code":"100002973","name":"Linguri lemn 16.5cm 12 buc","slug":"100002973-biodeck-linguri-lemn-16-5cm-12-buc"}],"activePromotion":null,"saveMe":null,"labels":[],"geniusPrice":null,"geniusUnitPricePerLabel":null,"banner":null,"discountLabel":null,"geniusDiscountLabel":null,"badge":null},{"code":"100002979","variantCode":"100002979","name":"Boluri de carton cu capace albe 115mm 480ml 6 buc","slug":"100002979-biodeck-boluri-de-carton-cu-capace-albe-115mm-480ml-6-buc","unitPriceLabel":"","brand":"Biodeck","brandCode":"299","brandFilterCode":"biodeck-b300","sku":"100002979","price":15.59,"originalPrice":null,"currencyCode":"RON","currency":"Lei","image":{"thumbnail":{"default":"https://cdn.freshful.ro/media/cache/sylius_shop_product_thumbnail/ba/ef/ce7a7bae4603d803c7d8e8a1767b.jpg"},"large":{"default":"https://cdn.freshful.ro/media/cache/freshful_large/ba/ef/ce7a7bae4603d803c7d8e8a1767b.jpg"},"extralarge":{"default":"https://cdn.freshful.ro/media/cache/sylius_shop_product_original/ba/ef/ce7a7bae4603d803c7d8e8a1767b.jpg"}},"label":null,"tags":[{"type":"bio","text":"Bio","icon":"https://cdn.freshful.ro/assets/product_tags/bio.svg","iconPng":"https://cdn.freshful.ro/assets/product_tags/bio.png","backgroundColor":"#ECF6E9","textColor":"#399225"}],"isAvailable":true,"maxAvailableQuantity":16,"maxAllowedQuantity":100,"breadcrumbs":[{"code":"14","name":"Casă și agrement","slug":"14-casa-si-agrement"},{"code":"1403","name":"Articole de menaj","slug":"1403-articole-de-menaj"},{"code":"140303","name":"Veselă de unică folosință","slug":"140303-vesela-de-unica-folosinta"},{"code":"100002979","name":"Boluri de carton cu capace albe 115mm 480ml 6 buc","slug":"100002979-biodeck-boluri-de-carton-cu-capace-albe-115mm-480ml-6-buc"}],"activePromotion":null,"saveMe":null,"labels":[],"geniusPrice":null,"geniusUnitPricePerLabel":null,"banner":null,"discountLabel":null,"geniusDiscountLabel":null,"badge":null},{"code":"100137981","variantCode":"100137981","name":"Pahare carton zero plastic bio Artwork 480ml, 25 buc","slug":"100137981-biodeck-pahare-carton-zero-plastic-bio-artwork-480ml-25-buc","unitPriceLabel":"","brand":"Biodeck","brandCode":"299","brandFilterCode":"biodeck-b300","sku":"100137981","price":25.99,"originalPrice":null,"currencyCode":"RON","currency":"Lei","image":{"thumbnail":{"default":"https://cdn.freshful.ro/media/cache/sylius_shop_product_thumbnail/2d/5f/b97782f3ea40f8ed3fe16b054866.jpg"},"large":{"default":"https://cdn.freshful.ro/media/cache/freshful_large/2d/5f/b97782f3ea40f8ed3fe16b054866.jpg"},"extralarge":{"default":"https://cdn.freshful.ro/media/cache/sylius_shop_product_original/2d/5f/b97782f3ea40f8ed3fe16b054866.jpg"}},"label":null,"tags":[{"type":"bio","text":"Bio","icon":"https://cdn.freshful.ro/assets/product_tags/bio.svg","iconPng":"https://cdn.freshful.ro/assets/product_tags/bio.png","backgroundColor":"#ECF6E9","textColor":"#399225"}],"isAvailable":true,"maxAvailableQuantity":64,"maxAllowedQuantity":100,"breadcrumbs":[{"code":"14","name":"Casă și agrement","slug":"14-casa-si-agrement"},{"code":"1403","name":"Articole de menaj","slug":"1403-articole-de-menaj"},{"code":"140303","name":"Veselă de unică folosință","slug":"140303-vesela-de-unica-folosinta"},{"code":"100137981","name":"Pahare carton zero plastic bio Artwork 480ml, 25 buc","slug":"100137981-biodeck-pahare-carton-zero-plastic-bio-artwork-480ml-25-buc"}],"activePromotion":null,"saveMe":null,"labels":[],"geniusPrice":null,"geniusUnitPricePerLabel":null,"banner":null,"discountLabel":null,"geniusDiscountLabel":null,"badge":null}],"analyticsListId":"product-slot_produse-similare","analyticsListName":"Product Slot - Produse similare"}],"metaTitle":"Farfurii biodegradabile din trestie de zahăr 12 buc - Prospețime și varietate","metaKeywords":null,"metaDescription":"Comandă Farfurii biodegradabile din trestie de zahăr 12 buc. Livrăm când dorești, cu mașini frigorifice. Gamă variată de bunătăți proaspete, de la producători locali. Hai pe Freshful.ro","code":"100137982","variantCode":"100137982","name":"Farfurii biodegradabile din trestie de zahăr 12 buc","slug":"100137982-biodeck-farfurii-biodegradabile-din-trestie-de-zahar-12-buc","unitPriceLabel":"","brand":"Biodeck","brandCode":"299","brandFilterCode":"biodeck-b300","sku":"100137982","price":7.89,"originalPrice":null,"currencyCode":"RON","currency":"Lei","image":{"thumbnail":{"default":"https://cdn.freshful.ro/media/cache/sylius_shop_product_thumbnail/46/ca/e65d876670208f252e3980e8465f.jpg"},"large":{"default":"https://cdn.freshful.ro/media/cache/freshful_large/46/ca/e65d876670208f252e3980e8465f.jpg"},"extralarge":{"default":"https://cdn.freshful.ro/media/cache/sylius_shop_product_original/46/ca/e65d876670208f252e3980e8465f.jpg"}},"label":null,"tags":[{"type":"bio","text":"Bio","icon":"https://cdn.freshful.ro/assets/product_tags/bio.svg","iconPng":"https://cdn.freshful.ro/assets/product_tags/bio.png","backgroundColor":"#ECF6E9","textColor":"#399225"}],"isAvailable":true,"maxAvailableQuantity":51,"maxAllowedQuantity":100,"breadcrumbs":[{"code":"14","name":"Casă și agrement","slug":"14-casa-si-agrement"},{"code":"1403","name":"Articole de menaj","slug":"1403-articole-de-menaj"},{"code":"140303","name":"Veselă de unică folosință","slug":"140303-vesela-de-unica-folosinta"},{"code":"100137982","name":"Farfurii biodegradabile din trestie de zahăr 12 buc","slug":"100137982-biodeck-farfurii-biodegradabile-din-trestie-de-zahar-12-buc"}],"activePromotion":null,"saveMe":null,"labels":[],"geniusPrice":null,"geniusUnitPricePerLabel":null,"banner":null,"discountLabel":null,"geniusDiscountLabel":null,"badge":null}